SNG/WB-SNG/LFSR4.v
module LFSR4(
    input clk,
    output reg [3:0] LFSR = 4'b0010
    );

    wire feedback = LFSR[3] ^ LFSR[2];

    always @(posedge clk)
        begin
        LFSR[0] <= feedback;
        LFSR[1] <= LFSR[0];
        LFSR[2] <= LFSR[1];
        LFSR[3] <= LFSR[2];
        end
endmodule

SNG/WB-SNG/WBG.v
module WBG (
    input clk,
    input reg [3:0] bn = 4'b1011,
    output sn,
    output [3:0] lfsr_out
    );

    wire l3, l2, l1, l0;
    wire w3, w2, w1, w0;
    wire o3, o2, o1, o0;

    assign lfsr_out = {l3, l2, l1, l0};
    
    LFSR4 lfsr(clk, {l3, l2, l1, l0});
    
    assign w3 = l3;
    assign w2 = l2 & !l3;
    assign w1 = l1 & !l2 & !l3;
    assign w0 = l0 & !l1 & !l2 & !l3;

    assign o3 = w3 & bn[3];
    assign o2 = w2 & bn[2];
    assign o1 = w1 & bn[1];
    assign o0 = w0 & bn[0];

    assign sn = o3 | o2 | o1 | o0;
    
endmodule

SNG/WB-SNG/wave.vcd
$version Generated by VerilatedVcd $end
$timescale 1s $end
 $scope module TOP $end
  $var wire 1 + clk $end
  $var wire 4 , bn [3:0] $end
  $var wire 1 - sn $end
  $var wire 4 . lfsr_out [3:0] $end
  $scope module WBG $end
   $var wire 1 + clk $end
   $var wire 4 , bn [3:0] $end
   $var wire 1 - sn $end
   $var wire 4 . lfsr_out [3:0] $end
   $var wire 1 " l3 $end
   $var wire 1 # l2 $end
   $var wire 1 $ l1 $end
   $var wire 1 % l0 $end
   $var wire 1 " w3 $end
   $var wire 1 & w2 $end
   $var wire 1 ' w1 $end
   $var wire 1 ( w0 $end
   $var wire 1 / o3 $end
   $var wire 1 0 o2 $end
   $var wire 1 1 o1 $end
   $var wire 1 2 o0 $end
   $scope module lfsr $end
    $var wire 1 + clk $end
    $var wire 4 ) LFSR [3:0] $end
    $var wire 1 * feedback $end
   $upscope $end
  $upscope $end
 $upscope $end
$enddefinitions $end


#0
0"
0#
1$
0%
0&
1'
0(
b0010 )
0*
1+
b1011 ,
1-
b0010 .
0/
00
11
02
#1
0+
#2
1#
0$
1&
0'
b0100 )
1*
1+
0-
b0100 .
01
#3
0+
#4
1"
0#
1%
0&
b1001 )
1+
1-
b1001 .
1/
#5
0+
#6
0"
1$
1'
b0011 )
0*
1+
b0011 .
0/
11
#7
0+
#8
1#
0%
1&
0'
b0110 )
1*
1+
0-
b0110 .
01
#9
0+
#10
1"
0$
1%
0&
b1101 )
0*
1+
1-
b1101 .
1/
#11
0+
#12
0#
1$
0%
b1010 )
1*
1+
b1010 .
#13
0+
#14
0"
1#
0$
1%
1&
b0101 )
1+
0-
b0101 .
0/
#15
0+
#16
1"
0#
1$
0&
b1011 )
1+
1-
b1011 .
1/
#17
0+
#18
0"
1#
1&
b0111 )
1+
0-
b0111 .
0/
#19
0+
#20
1"
0&
b1111 )
0*
1+
1-
b1111 .
1/
#21
0+
#22
0%
b1110 )
1+
b1110 .
#23
0+
#24
0$
b1100 )
1+
b1100 .
#25
0+
#26
0#
b1000 )
1*
1+
b1000 .
#27
0+
#28
0"
1%
1(
b0001 )
0*
1+
b0001 .
0/
12
#29
0+
#30
1$
0%
1'
0(
b0010 )
1+
b0010 .
11
02
