LFSR/LFSR_4bits/LFSR4.v
module LFSR4(
    input clk,
    output reg [3:0] LFSR = 4'b0010
    );

    wire feedback = LFSR[0] ^ LFSR[1];

    always @(posedge clk)
        begin
        LFSR[0] <= LFSR[1];
        LFSR[1] <= LFSR[2];
        LFSR[2] <= LFSR[3];
        LFSR[3] <= feedback;
        end
endmodule

LFSR/LFSR_4bits/wave.vcd
$version Generated by VerilatedVcd $end
$timescale 1s $end
 $scope module TOP $end
  $var wire 1 " clk $end
  $var wire 4 # LFSR [3:0] $end
  $scope module LFSR4 $end
   $var wire 1 " clk $end
   $var wire 4 # LFSR [3:0] $end
   $var wire 1 $ feedback $end
  $upscope $end
 $upscope $end
$enddefinitions $end


#0
1"
b0010 #
1$
#1
0"
#2
1"
b1001 #
#3
0"
#4
1"
b1100 #
0$
#5
0"
#6
1"
b0110 #
1$
#7
0"
#8
1"
b1011 #
0$
#9
0"
#10
1"
b0101 #
1$
#11
0"
#12
1"
b1010 #
#13
0"
#14
1"
b1101 #
