LFSR/LFSR_8bits/LFSR8.v
module LFSR8(
    input clk,
    output reg [7:0] LFSR = 8'b10001010
    );

    wire feedback = LFSR[0] ^ LFSR[1];

    always @(posedge clk)
        begin
        LFSR[0] <= LFSR[1];
        LFSR[1] <= LFSR[2];
        LFSR[2] <= LFSR[3];
        LFSR[3] <= LFSR[4];
        LFSR[4] <= LFSR[5];
        LFSR[5] <= LFSR[6];
        LFSR[6] <= LFSR[7];
        LFSR[7] <= feedback;
        end
endmodule

LFSR/LFSR_8bits/wave.vcd
$version Generated by VerilatedVcd $end
$timescale 1s $end
 $scope module TOP $end
  $var wire 1 " clk $end
  $var wire 8 # LFSR [7:0] $end
  $scope module LFSR8 $end
   $var wire 1 " clk $end
   $var wire 8 # LFSR [7:0] $end
   $var wire 1 $ feedback $end
  $upscope $end
 $upscope $end
$enddefinitions $end


#0
1"
b10001010 #
1$
#1
0"
#2
1"
b11000101 #
#3
0"
#4
1"
b11100010 #
#5
0"
#6
1"
b11110001 #
#7
0"
#8
1"
b11111000 #
0$
#9
0"
#10
1"
b01111100 #
#11
0"
#12
1"
b00111110 #
1$
#13
0"
#14
1"
b10011111 #
0$
#15
0"
#16
1"
b01001111 #
#17
0"
#18
1"
b00100111 #
#19
0"
#20
1"
b00010011 #
#21
0"
#22
1"
b00001001 #
1$
